geobrix/__init__.py
geobrix-0.0.0.dist-info/METADATA
geobrix-0.0.0.dist-info/WHEEL
geobrix-0.0.0.dist-info/top_level.txt
geobrix-0.0.0.dist-info/RECORD
