Metadata-Version: 2.4
Name: geobrix
Version: 0.0.0
Summary: Coming soon
Author-email: Michael Johns <mjohns@databricks.com>
